src/__init__.py
src/config_ui/index.html
src/direct_api_server.py
src/exporters/__init__.py
src/exporters/notion_exporter.py
src/exporters/obsidian_exporter.py
src/exporters/pdf_exporter.py
src/extractors/__init__.py
src/extractors/web.py
src/models/__init__.py
src/models/conversation.py
src/models.py
src/search/__init__.py
src/search/search_engine.py
src/search/semantic_search.py
src/search/text_search.py
src/utils/__init__.py
src/utils/rate_limiter.py
src/utils/request_queue.py
src/utils.py
mcp_claude_context-0.5.4.dist-info/LICENSE
mcp_claude_context-0.5.4.dist-info/METADATA
mcp_claude_context-0.5.4.dist-info/WHEEL
mcp_claude_context-0.5.4.dist-info/entry_points.txt
mcp_claude_context-0.5.4.dist-info/RECORD
