Metadata-Version: 2.3
Name: mcp-claude-context
Version: 0.5.4
Summary: MCP server for Claude conversation extraction with enhanced export and search
License: MIT
Keywords: mcp,claude,anthropic,conversation,export
Author: Hamza Azhar Amjad
Requires-Python: >=3.11,<4.0
Classifier: Development Status :: 4 - Beta
Classifier: Intended Audience :: Developers
Classifier: License :: OSI Approved :: MIT License
Classifier: Programming Language :: Python :: 3
Classifier: Programming Language :: Python :: 3.11
Classifier: Programming Language :: Python :: 3.12
Classifier: Programming Language :: Python :: 3.13
Classifier: Topic :: Software Development :: Libraries :: Python Modules
Requires-Dist: aiohttp (>=3.9.0,<4.0.0)
Requires-Dist: aiohttp-cors (>=0.8.1,<0.9.0)
Requires-Dist: aiosqlite (>=0.19.0,<0.20.0)
Requires-Dist: beautifulsoup4 (>=4.12.0,<5.0.0)
Requires-Dist: brotli (>=1.1.0,<2.0.0)
Requires-Dist: faiss-cpu (>=1.7.4,<2.0.0)
Requires-Dist: mcp (>=1.0.0,<2.0.0)
Requires-Dist: openpyxl (>=3.1.0,<4.0.0)
Requires-Dist: pandas (>=2.0.0,<3.0.0)
Requires-Dist: playwright (>=1.40.0,<2.0.0)
Requires-Dist: pydantic (>=2.5.0,<3.0.0)
Requires-Dist: redis (>=5.0.0,<6.0.0)
Requires-Dist: reportlab (>=4.0.0,<5.0.0)
Requires-Dist: requests (>=2.32.3,<3.0.0)
Requires-Dist: sentence-transformers (>=2.2.0,<3.0.0)
Requires-Dist: sqlalchemy (>=2.0.0,<3.0.0)
Requires-Dist: watchdog (>=3.0.0,<4.0.0)
Project-URL: Bug Tracker, https://github.com/hamzaamjad/mcp-claude-context/issues
Project-URL: Changelog, https://github.com/hamzaamjad/mcp-claude-context/blob/main/CHANGELOG.md
Project-URL: Documentation, https://github.com/hamzaamjad/mcp-claude-context/tree/main/docs
Project-URL: Homepage, https://github.com/hamzaamjad/mcp-claude-context
Project-URL: Repository, https://github.com/hamzaamjad/mcp-claude-context
